{
  "version": "7",
  "dialect": "postgresql",
  "entries": [
    {
      "idx": 0,
      "version": "7",
      "when": 1775324713991,
      "tag": "0000_fluffy_ultimo",
      "breakpoints": true
    },
    {
      "idx": 1,
      "version": "7",
      "when": 1775404042058,
      "tag": "0001_nasty_meggan",
      "breakpoints": true
    },
    {
      "idx": 2,
      "version": "7",
      "when": 1775405429843,
      "tag": "0002_flimsy_hydra",
      "breakpoints": true
    },
    {
      "idx": 3,
      "version": "7",
      "when": 1775499622554,
      "tag": "0003_shocking_salo",
      "breakpoints": true
    },
    {
      "idx": 4,
      "version": "7",
      "when": 1775502806537,
      "tag": "0004_daily_proemial_gods",
      "breakpoints": true
    },
    {
      "idx": 5,
      "version": "7",
      "when": 1775540762137,
      "tag": "0005_odd_harry_osborn",
      "breakpoints": true
    },
    {
      "idx": 6,
      "version": "7",
      "when": 1775553975921,
      "tag": "0006_dapper_karnak",
      "breakpoints": true
    }
  ]
}